mroi_fd/__init__.py
mroi_fd/_utils.py
mroi_fd/face_detector.py
mroi_fd/routines.py
mroi_fd-1.0.0.post3.dist-info/LICENSE
mroi_fd-1.0.0.post3.dist-info/METADATA
mroi_fd-1.0.0.post3.dist-info/WHEEL
mroi_fd-1.0.0.post3.dist-info/top_level.txt
mroi_fd-1.0.0.post3.dist-info/RECORD
