Metadata-Version: 2.1
Name: mroi-fd
Version: 1.0.0.post3
Summary: 
Home-page: https://gitlab.com/ailabuser/bacha-hybrid-mroi-face-detection
Author: ailabuser
Author-email: lab@ailab.space
License: UNKNOWN
Platform: UNKNOWN
Classifier: Programming Language :: Python :: 3
Classifier: License :: OSI Approved :: MIT License
Classifier: Operating System :: Microsoft :: Windows :: Windows 10
Classifier: Operating System :: Unix
Requires-Python: >=3.7.0
Requires-Dist: opencv-python (>=4.1.1.26)
Requires-Dist: numpy (>=1.17.2)
Requires-Dist: mtcnn (>=0.1.0)
Requires-Dist: pandas (>=0.25.2)
Requires-Dist: llist (>=0.6)
Requires-Dist: tensorflow (>=2.0.0)
